async_its_logger/__init__.py
async_its_logger/main.py
async_its_logger/its_logger/__init__.py
async_its_logger/its_logger/async_its_logger.py
async_its_logger/its_logger/log_observer.py
async_its_logger/its_logger/observers/__init__.py
async_its_logger/its_logger/observers/console_observer.py
async_its_logger/its_logger/observers/datadog_observer.py
async_its_logger/its_logger/observers/local_file_observer.py
async_its_logger/its_logger/observers/mongodb_observer.py
async_its_logger/its_logger/observers/redis_observer.py
async_its_logger/its_logger/observers/s3_observer.py
async_its_logger-0.1.1.dist-info/LICENSE
async_its_logger-0.1.1.dist-info/METADATA
async_its_logger-0.1.1.dist-info/WHEEL
async_its_logger-0.1.1.dist-info/top_level.txt
async_its_logger-0.1.1.dist-info/RECORD
