Metadata-Version: 2.2
Name: async_its_logger
Version: 0.1.1
Summary: Asynchronous logger for high performance applications that incorporates multiple observers, logs in batches, and includes automatic retries and fallback if services are not available.
Home-page: https://github.com/inmediatum/asynch_its_logger.git
Author: Cristopher Serrato
Author-email: cristopher.serrato@inmediatum.com
Classifier: Programming Language :: Python :: 3
Classifier: License :: OSI Approved :: MIT License
Classifier: Operating System :: OS Independent
Requires-Python: >=3.7
License-File: LICENSE
Requires-Dist: pymongo
Requires-Dist: redis
Requires-Dist: boto3
Requires-Dist: datadog-api-client
Requires-Dist: pyyaml
Requires-Dist: certifi
Dynamic: author
Dynamic: author-email
Dynamic: classifier
Dynamic: description
Dynamic: description-content-type
Dynamic: home-page
Dynamic: requires-dist
Dynamic: requires-python
Dynamic: summary
